{
    "LB1761": {
    "name": "LB1761",
    "diameter": 25.4,
    "r0": 24.5,
    "k0": 0,
    "a0": [],
    "thickness": 9.0,
    "material": "N-BK7",
    "type": "biconvex",
      "focalLength": 25.4,
      "description": "N-BK7 Bi-Convex Lens, Ø1\", f = 25.4 mm, Uncoated"
  },
    "LB1757": {
    "name": "LB1757",
    "diameter": 25.4,
    "r0": 29.5,
    "k0": 0,
    "a0": [],
    "thickness": 7.7,
    "material": "N-BK7",
    "type": "biconvex",
      "focalLength": 30,
      "description": "N-BK7 Bi-Convex Lens, Ø1\", f = 30.0 mm, Uncoated"
  },
    "LB1811": {
    "name": "LB1811",
    "diameter": 25.4,
    "r0": 34.9,
    "k0": 0,
    "a0": [],
    "thickness": 6.8,
    "material": "N-BK7",
    "type": "biconvex",
      "focalLength": 35,
      "description": "N-BK7 Bi-Convex Lens, Ø1\", f = 35.0 mm, Uncoated"
  },
    "LB1027": {
    "name": "LB1027",
    "diameter": 25.4,
    "r0": 40.1,
    "k0": 0,
    "a0": [],
    "thickness": 6.1,
    "material": "N-BK7",
    "type": "biconvex",
      "focalLength": 40,
      "description": "N-BK7 Bi-Convex Lens, Ø1\", f = 40.0 mm, Uncoated"
  },
    "LB1471": {
    "name": "LB1471",
    "diameter": 25.4,
    "r0": 50.6,
    "k0": 0,
    "a0": [],
    "thickness": 5.2,
    "material": "N-BK7",
    "type": "biconvex",
      "focalLength": 50,
      "description": "N-BK7 Bi-Convex Lens, Ø1\", f = 50.0 mm, Uncoated"
  },
    "LB1596": {
    "name": "LB1596",
    "diameter": 25.4,
    "r0": 61.0,
    "k0": 0,
    "a0": [],
    "thickness": 4.7,
    "material": "N-BK7",
    "type": "biconvex",
      "focalLength": 60,
      "description": "N-BK7 Bi-Convex Lens, Ø1\", f = 60.0 mm, Uncoated"
  },
    "LB1901": {
    "name": "LB1901",
    "diameter": 25.4,
    "r0": 76.6,
    "k0": 0,
    "a0": [],
    "thickness": 4.1,
    "material": "N-BK7",
    "type": "biconvex",
      "focalLength": 75,
      "description": "N-BK7 Bi-Convex Lens, Ø1\", f = 75.0 mm, Uncoated"
  },
  "LB1676": {
    "name": "LB1676",
    "diameter": 25.4,
    "r0": 102.4,
    "k0": 0,
    "a0": [],
    "thickness": 3.6,
    "material": "N-BK7",
    "type": "biconvex",
      "focalLength": 100,
      "description": "N-BK7 Bi-Convex Lens, Ø1\", f = 100.0 mm, Uncoated"
  },
  "LB1904": {
    "name": "LB1904",
    "diameter": 25.4,
    "r0": 128.2,
    "k0": 0,
    "a0": [],
    "thickness": 3.3,
    "material": "N-BK7",
    "type": "biconvex",
      "focalLength": 125,
      "description": "N-BK7 Bi-Convex Lens, Ø1\", f = 125.0 mm, Uncoated"
  },
  "LB1437": {
    "name": "LB1437",
    "diameter": 25.4,
    "r0": 154.0,
    "k0": 0,
    "a0": [],
    "thickness": 3.1,
    "material": "N-BK7",
    "type": "biconvex",
      "focalLength": 150,
      "description": "N-BK7 Bi-Convex Lens, Ø1\", f = 150.0 mm, Uncoated"
  },
  "LB1294": {
    "name": "LB1294",
    "diameter": 25.4,
    "r0": 179.8,
    "k0": 0,
    "a0": [],
    "thickness": 2.9,
    "material": "N-BK7",
    "type": "biconvex",
      "focalLength": 175,
      "description": "N-BK7 Bi-Convex Lens, Ø1\", f = 175.0 mm, Uncoated"
  },
  "LB1945": {
    "name": "LB1945",
    "diameter": 25.4,
    "r0": 205.6,
    "k0": 0,
    "a0": [],
    "thickness": 2.8,
    "material": "N-BK7",
    "type": "biconvex",
      "focalLength": 200,
      "description": "N-BK7 Bi-Convex Lens, Ø1\", f = 200.0 mm, Uncoated"
  },
  "LB1056": {
    "name": "LB1056",
    "diameter": 25.4,
    "r0": 257.1,
    "k0": 0,
    "a0": [],
    "thickness": 2.6,
    "material": "N-BK7",
    "type": "biconvex",
      "focalLength": 250,
      "description": "N-BK7 Bi-Convex Lens, Ø1\", f = 250.0 mm, Uncoated"
  },
  "LB1779": {
    "name": "LB1779",
    "diameter": 25.4,
    "r0": 308.6,
    "k0": 0,
    "a0": [],
    "thickness": 2.5,
    "material": "N-BK7",
    "type": "biconvex",
      "focalLength": 300,
      "description": "N-BK7 Bi-Convex Lens, Ø1\", f = 300.0 mm, Uncoated"
  },
  "LB1391": {
    "name": "LB1391",
    "diameter": 25.4,
    "r0": 411.7,
    "k0": 0,
    "a0": [],
    "thickness": 2.4,
    "material": "N-BK7",
    "type": "biconvex",
      "focalLength": 400,
      "description": "N-BK7 Bi-Convex Lens, Ø1\", f = 400.0 mm, Uncoated"
  },
  "LB1869": {
    "name": "LB1869",
    "diameter": 25.4,
    "r0": 514.7,
    "k0": 0,
    "a0": [],
    "thickness": 2.3,
    "material": "N-BK7",
    "type": "biconvex",
      "focalLength": 500,
      "description": "N-BK7 Bi-Convex Lens, Ø1\", f = 500.0 mm, Uncoated"
  },
  "LB1475": {
    "name": "LB1475",
    "diameter": 25.4,
    "r0": 772.2,
    "k0": 0,
    "a0": [],
    "thickness": 2.2,
    "material": "N-BK7",
    "type": "biconvex",
      "focalLength": 750,
      "description": "N-BK7 Bi-Convex Lens, Ø1\", f = 750.0 mm, Uncoated"
  },
  "LB1409": {
    "name": "LB1409",
    "diameter": 25.4,
    "r0": 1029.8,
    "k0": 0,
    "a0": [],
    "thickness": 2.2,
    "material": "N-BK7",
    "type": "biconvex",
      "focalLength": 1000,
      "description": "N-BK7 Bi-Convex Lens, Ø1\", f = 1000.0 mm, Uncoated"
  }
}